pyconfluent/__init__.py
pyconfluent/ksql.py
pyconfluent/schema_registry.py
pyconfluent/kafka_streams/__init__.py
pyconfluent/kafka_streams/kafka_client_supplier.py
pyconfluent/kafka_streams/kafka_config.py
pyconfluent/kafka_streams/kafka_streams.py
pyconfluent/kafka_streams/errors/__init__.py
pyconfluent/kafka_streams/errors/_kafka_error_codes.py
pyconfluent/kafka_streams/errors/kafka_streams_error.py
pyconfluent/kafka_streams/errors/task_migrated_error.py
pyconfluent/kafka_streams/processor/__init__.py
pyconfluent/kafka_streams/processor/_context.py
pyconfluent/kafka_streams/processor/_punctuation_queue.py
pyconfluent/kafka_streams/processor/_record_collector.py
pyconfluent/kafka_streams/processor/_stream_task.py
pyconfluent/kafka_streams/processor/_stream_thread.py
pyconfluent/kafka_streams/processor/_timestamp.py
pyconfluent/kafka_streams/processor/extract_timestamp.py
pyconfluent/kafka_streams/processor/processor.py
pyconfluent/kafka_streams/processor/processor_context.py
pyconfluent/kafka_streams/processor/task_id.py
pyconfluent/kafka_streams/processor/topology.py
pyconfluent/kafka_streams/processor/wallclock_timestamp.py
pyconfluent/kafka_streams/processor/serialization/__init__.py
pyconfluent/kafka_streams/processor/serialization/_avro.py
pyconfluent/kafka_streams/processor/serialization/_bytes.py
pyconfluent/kafka_streams/processor/serialization/_double.py
pyconfluent/kafka_streams/processor/serialization/_float.py
pyconfluent/kafka_streams/processor/serialization/_integer.py
pyconfluent/kafka_streams/processor/serialization/_json.py
pyconfluent/kafka_streams/processor/serialization/_long.py
pyconfluent/kafka_streams/processor/serialization/_string.py
pyconfluent/kafka_streams/processor/serialization/deserializer.py
pyconfluent/kafka_streams/processor/serialization/serde.py
pyconfluent/kafka_streams/processor/serialization/serializer.py
pyconfluent/kafka_streams/processor/serialization/serdes/__init__.py
pyconfluent-0.0.6.dist-info/LICENSE
pyconfluent-0.0.6.dist-info/METADATA
pyconfluent-0.0.6.dist-info/WHEEL
pyconfluent-0.0.6.dist-info/top_level.txt
pyconfluent-0.0.6.dist-info/RECORD
