Metadata-Version: 2.1
Name: pyconfluent
Version: 0.0.6
Summary: UNKNOWN
Home-page: https://gitbub.com/newellp2019/pyconfluent
Author: Peter Newell
Author-email: peter.newell@covetrus.com
License: UNKNOWN
Platform: UNKNOWN
Classifier: Programming Language :: Python :: 3
Classifier: License :: OSI Approved :: MIT License
Classifier: Operating System :: OS Independent
Requires-Dist: requests
Requires-Dist: confluent-kafka[avro]
Requires-Dist: avro-python3
